ga4_data_import/__init__.py
ga4_data_import/common.py
ga4_data_import/compute.py
ga4_data_import/storage.py
ga4_data_import/workflow.py
ga4_data_import-0.1.66.dist-info/LICENSE
ga4_data_import-0.1.66.dist-info/METADATA
ga4_data_import-0.1.66.dist-info/WHEEL
ga4_data_import-0.1.66.dist-info/top_level.txt
ga4_data_import-0.1.66.dist-info/RECORD
