Metadata-Version: 2.1
Name: ga4_data_import
Version: 0.1.66
Summary: Google Analytics 4 Data Import pipeline
Author-email: Max Ostapenko <ga4_data_import@maxostapenko.com>
License: GNU GENERAL PUBLIC LICENSE
Project-URL: Source, https://github.com/max-ostapenko/ga4_data_import/
Project-URL: Modules Documentation, https://github.com/max-ostapenko/ga4_data_import/blob/main/docs/index.md
Project-URL: Bug Reports, https://github.com/max-ostapenko/ga4_data_import/issues
Project-URL: Project website, https://maxostapenko.com/projects/google_analytics_4_data_import/
Keywords: Google Analytics 4,Data Import,SFTP,Google Cloud Storage
Classifier: Development Status :: 3 - Alpha
Classifier: License :: OSI Approved :: GNU General Public License v3 or later (GPLv3+)
Classifier: Programming Language :: Python :: 3
Classifier: Programming Language :: Python :: 3.9
Classifier: Programming Language :: Python :: 3.10
Classifier: Programming Language :: Python :: 3.11
Classifier: Topic :: Internet :: File Transfer Protocol (FTP)
Classifier: Topic :: Utilities
Requires-Python: >=3.7
License-File: LICENSE
Requires-Dist: google-cloud-compute
Requires-Dist: google-cloud-resource-manager
Requires-Dist: google-cloud-storage
Requires-Dist: google-cloud-workflows
Requires-Dist: google-cloud-scheduler
Requires-Dist: google-cloud-core
Provides-Extra: dev
Requires-Dist: check-manifest ; extra == 'dev'
Requires-Dist: build ; extra == 'dev'
Requires-Dist: twine ; extra == 'dev'
Provides-Extra: test
Requires-Dist: coverage ; extra == 'test'
